{
    "Populations": [
        {
            "Size": 10,
            "Solutions": [
                {
                    "Constraints Evaluated": true,
                    "Cost": 0.10398666378921778,
                    "Decision Vec": [
                        {
                            "type": "Real Type",
                            "value": 0.075428362360985268
                        },
                        {
                            "type": "Real Type",
                            "value": 0.073647226027024199
                        },
                        {
                            "type": "Real Type",
                            "value": 2.1312608130798907
                        },
                        {
                            "type": "Real Type",
                            "value": 1.1654307093105483
                        },
                        {
                            "type": "Real Type",
                            "value": 8.1602506169822213
                        }
                    ],
                    "Objective Vec": [
                        {
                            "type": "Real Type",
                            "value": 1.6900133252722735
                        },
                        {
                            "type": "Real Type",
                            "value": 2.8306892483255126
                        }
                    ],
                    "Objectives Evaluated": true,
                    "Parameter Vec": [
                    ],
                    "Run Number": 1,
                    "Scalarised": false,
                    "Solution Evaluated": true,
                    "Unused Vec": [
                    ],
                    "Weight Vec": [
                        0.88888888888888884,
                        0.1111111111111111
                    ]
                },
                {
                    "Constraints Evaluated": true,
                    "Cost": 0.10398666378921778,
                    "Decision Vec": [
                        {
                            "type": "Real Type",
                            "value": 0.075428362360985268
                        },
                        {
                            "type": "Real Type",
                            "value": 0.073647226027024199
                        },
                        {
                            "type": "Real Type",
                            "value": 2.1312608130798907
                        },
                        {
                            "type": "Real Type",
                            "value": 1.1654307093105483
                        },
                        {
                            "type": "Real Type",
                            "value": 8.1602506169822213
                        }
                    ],
                    "Objective Vec": [
                        {
                            "type": "Real Type",
                            "value": 1.6900133252722735
                        },
                        {
                            "type": "Real Type",
                            "value": 2.8306892483255126
                        }
                    ],
                    "Objectives Evaluated": true,
                    "Parameter Vec": [
                    ],
                    "Run Number": 1,
                    "Scalarised": false,
                    "Solution Evaluated": true,
                    "Unused Vec": [
                    ],
                    "Weight Vec": [
                        0.88888888888888884,
                        0.1111111111111111
                    ]
                },
                {
                    "Constraints Evaluated": true,
                    "Cost": 0.35852338634513042,
                    "Decision Vec": [
                        {
                            "type": "Real Type",
                            "value": 0.17077682901717545
                        },
                        {
                            "type": "Real Type",
                            "value": 0.33291755391561406
                        },
                        {
                            "type": "Real Type",
                            "value": 2.1065593491246126
                        },
                        {
                            "type": "Real Type",
                            "value": 1.1906951746046976
                        },
                        {
                            "type": "Real Type",
                            "value": 8.1891310596020048
                        }
                    ],
                    "Objective Vec": [
                        {
                            "type": "Real Type",
                            "value": 1.4263461701083517
                        },
                        {
                            "type": "Real Type",
                            "value": 3.310308404065343
                        }
                    ],
                    "Objectives Evaluated": true,
                    "Parameter Vec": [
                    ],
                    "Run Number": 1,
                    "Scalarised": false,
                    "Solution Evaluated": true,
                    "Unused Vec": [
                    ],
                    "Weight Vec": [
                        0.66666666666666663,
                        0.33333333333333331
                    ]
                },
                {
                    "Constraints Evaluated": true,
                    "Cost": 0.45298689746670273,
                    "Decision Vec": [
                        {
                            "type": "Real Type",
                            "value": 1.3941351622804028
                        },
                        {
                            "type": "Real Type",
                            "value": 2.985124693865941
                        },
                        {
                            "type": "Real Type",
                            "value": 1.60862682186793
                        },
                        {
                            "type": "Real Type",
                            "value": 5.2275259397131766
                        },
                        {
                            "type": "Real Type",
                            "value": 4.0362409978046134
                        }
                    ],
                    "Objective Vec": [
                        {
                            "type": "Real Type",
                            "value": 1.2438018241066022
                        },
                        {
                            "type": "Real Type",
                            "value": 3.4690706262226105
                        }
                    ],
                    "Objectives Evaluated": true,
                    "Parameter Vec": [
                    ],
                    "Run Number": 1,
                    "Scalarised": false,
                    "Solution Evaluated": true,
                    "Unused Vec": [
                    ],
                    "Weight Vec": [
                        0.5,
                        0.5
                    ]
                },
                {
                    "Constraints Evaluated": true,
                    "Cost": 0.23436535015048751,
                    "Decision Vec": [
                        {
                            "type": "Real Type",
                            "value": 1.9564487230798493
                        },
                        {
                            "type": "Real Type",
                            "value": 3.5810705858851963
                        },
                        {
                            "type": "Real Type",
                            "value": 1.4297590954648063
                        },
                        {
                            "type": "Real Type",
                            "value": 4.4894844280882298
                        },
                        {
                            "type": "Real Type",
                            "value": 3.981071988432193
                        }
                    ],
                    "Objective Vec": [
                        {
                            "type": "Real Type",
                            "value": 1.4913402716378561
                        },
                        {
                            "type": "Real Type",
                            "value": 3.1026593217927867
                        }
                    ],
                    "Objectives Evaluated": true,
                    "Parameter Vec": [
                    ],
                    "Run Number": 1,
                    "Scalarised": false,
                    "Solution Evaluated": true,
                    "Unused Vec": [
                    ],
                    "Weight Vec": [
                        0.44444444444444442,
                        0.55555555555555558
                    ]
                },
                {
                    "Constraints Evaluated": true,
                    "Cost": 0.74447448455169263,
                    "Decision Vec": [
                        {
                            "type": "Real Type",
                            "value": 1.0858331616326757
                        },
                        {
                            "type": "Real Type",
                            "value": 2.175143932103504
                        },
                        {
                            "type": "Real Type",
                            "value": 2.0998065613522976
                        },
                        {
                            "type": "Real Type",
                            "value": 4.2547963983274801
                        },
                        {
                            "type": "Real Type",
                            "value": 4.0493806761002418
                        }
                    ],
                    "Objective Vec": [
                        {
                            "type": "Real Type",
                            "value": 0.48653002893710073
                        },
                        {
                            "type": "Real Type",
                            "value": 3.9600968171812099
                        }
                    ],
                    "Objectives Evaluated": true,
                    "Parameter Vec": [
                    ],
                    "Run Number": 1,
                    "Scalarised": false,
                    "Solution Evaluated": true,
                    "Unused Vec": [
                    ],
                    "Weight Vec": [
                        0.33333333333333331,
                        0.66666666666666663
                    ]
                },
                {
                    "Constraints Evaluated": true,
                    "Cost": 0.58971293531647717,
                    "Decision Vec": [
                        {
                            "type": "Real Type",
                            "value": 1.1153672458834634
                        },
                        {
                            "type": "Real Type",
                            "value": 2.8081639564634182
                        },
                        {
                            "type": "Real Type",
                            "value": 2.0951090835871762
                        },
                        {
                            "type": "Real Type",
                            "value": 5.3464478860096847
                        },
                        {
                            "type": "Real Type",
                            "value": 4.1764301870797258
                        }
                    ],
                    "Objective Vec": [
                        {
                            "type": "Real Type",
                            "value": 1.0630664923079074
                        },
                        {
                            "type": "Real Type",
                            "value": 3.6983756091156108
                        }
                    ],
                    "Objectives Evaluated": true,
                    "Parameter Vec": [
                    ],
                    "Run Number": 1,
                    "Scalarised": false,
                    "Solution Evaluated": true,
                    "Unused Vec": [
                    ],
                    "Weight Vec": [
                        0.44444444444444442,
                        0.55555555555555558
                    ]
                },
                {
                    "Constraints Evaluated": true,
                    "Cost": 0.91051941964642447,
                    "Decision Vec": [
                        {
                            "type": "Real Type",
                            "value": 0.6928767867696648
                        },
                        {
                            "type": "Real Type",
                            "value": 1.3266126031484959
                        },
                        {
                            "type": "Real Type",
                            "value": 1.9413543351680418
                        },
                        {
                            "type": "Real Type",
                            "value": 1.2784884635145368
                        },
                        {
                            "type": "Real Type",
                            "value": 7.5085767818173563
                        }
                    ],
                    "Objective Vec": [
                        {
                            "type": "Real Type",
                            "value": 0.38448687016072536
                        },
                        {
                            "type": "Real Type",
                            "value": 4.2378881389540251
                        }
                    ],
                    "Objectives Evaluated": true,
                    "Parameter Vec": [
                    ],
                    "Run Number": 1,
                    "Scalarised": false,
                    "Solution Evaluated": true,
                    "Unused Vec": [
                    ],
                    "Weight Vec": [
                        0.1111111111111111,
                        0.88888888888888884
                    ]
                },
                {
                    "Constraints Evaluated": true,
                    "Cost": 0.67808414529873029,
                    "Decision Vec": [
                        {
                            "type": "Real Type",
                            "value": 1.0737360561978684
                        },
                        {
                            "type": "Real Type",
                            "value": 2.7074785403079273
                        },
                        {
                            "type": "Real Type",
                            "value": 2.1017360265900975
                        },
                        {
                            "type": "Real Type",
                            "value": 4.9745260634096518
                        },
                        {
                            "type": "Real Type",
                            "value": 3.9986929279362884
                        }
                    ],
                    "Objective Vec": [
                        {
                            "type": "Real Type",
                            "value": 0.74543557645508662
                        },
                        {
                            "type": "Real Type",
                            "value": 3.8477549029711713
                        }
                    ],
                    "Objectives Evaluated": true,
                    "Parameter Vec": [
                    ],
                    "Run Number": 1,
                    "Scalarised": false,
                    "Solution Evaluated": true,
                    "Unused Vec": [
                    ],
                    "Weight Vec": [
                        0.22222222222222221,
                        0.77777777777777779
                    ]
                },
                {
                    "Constraints Evaluated": true,
                    "Cost": 0.74447448455169263,
                    "Decision Vec": [
                        {
                            "type": "Real Type",
                            "value": 1.0858331616326757
                        },
                        {
                            "type": "Real Type",
                            "value": 2.175143932103504
                        },
                        {
                            "type": "Real Type",
                            "value": 2.0998065613522976
                        },
                        {
                            "type": "Real Type",
                            "value": 4.2547963983274801
                        },
                        {
                            "type": "Real Type",
                            "value": 4.0493806761002418
                        }
                    ],
                    "Objective Vec": [
                        {
                            "type": "Real Type",
                            "value": 0.48653002893710073
                        },
                        {
                            "type": "Real Type",
                            "value": 3.9600968171812099
                        }
                    ],
                    "Objectives Evaluated": true,
                    "Parameter Vec": [
                    ],
                    "Run Number": 1,
                    "Scalarised": false,
                    "Solution Evaluated": true,
                    "Unused Vec": [
                    ],
                    "Weight Vec": [
                        0.33333333333333331,
                        0.66666666666666663
                    ]
                }
            ],
            "Tags": "",
            "Time": "Tue Oct  9 18:55:54 2018\n"
        }
    ]
}
